gowpy/__init__.py
gowpy/feature_extraction/__init__.py
gowpy/feature_extraction/gow/__init__.py
gowpy/feature_extraction/gow/gow_vectorizer.py
gowpy/feature_extraction/gow/tw_vectorizer.py
gowpy/gow/__init__.py
gowpy/gow/builder.py
gowpy/gow/io.py
gowpy/gow/miner.py
gowpy/gow/typing.py
gowpy/summarization/__init__.py
gowpy/summarization/unsupervised/__init__.py
gowpy/summarization/unsupervised/algorithms.py
gowpy/summarization/unsupervised/helpers.py
gowpy/summarization/unsupervised/keyword_extractor_corerank.py
gowpy/summarization/unsupervised/keyword_extractor_gow.py
gowpy/summarization/unsupervised/keyword_extractor_kcore.py
gowpy/utils/__init__.py
gowpy/utils/defaults.py
gowpy-0.2.0.dist-info/METADATA
gowpy-0.2.0.dist-info/RECORD
gowpy-0.2.0.dist-info/WHEEL
gowpy-0.2.0.dist-info/top_level.txt
