Metadata-Version: 2.1
Name: gowpy
Version: 0.2.0
Summary: A very simple graph-of-words library for NLP
Home-page: https://github.com/GuillaumeDD/gowpy.git
Author: Guillaume Dubuisson Duplessis
Author-email: guillaume@dubuissonduplessis.fr
License: new BSD
Platform: UNKNOWN
Classifier: Development Status :: 3 - Alpha
Classifier: Intended Audience :: Developers
Classifier: Intended Audience :: Education
Classifier: Intended Audience :: Science/Research
Classifier: License :: OSI Approved :: BSD License
Classifier: Programming Language :: Python :: 3
Classifier: Programming Language :: Python :: 3.6
Classifier: Programming Language :: Python :: 3.7
Classifier: Topic :: Software Development :: Libraries
Classifier: Topic :: Software Development :: Libraries :: Python Modules
Requires-Python: >=3.6
Requires-Dist: networkx (>=2.4)
Requires-Dist: scikit-learn (>=0.22.2)
Requires-Dist: matplotlib (>=3.1)
